gridmarthe/gridmarthe.py
gridmarthe/plot.py
gridmarthe/utils.py
gridmarthe/__init__.py
gridmarthe/__version__.py
gridmarthe/lecsem/edsemigl.f90
gridmarthe/lecsem/lecsem.cp313-win_amd64.dll.a
gridmarthe/lecsem/lecsem.cp313-win_amd64.pyd
gridmarthe/lecsem/lecsem.f90
gridmarthe/lecsem/scan_grid.f90
gridmarthe/lecsem/_parse_gridmarthe.py
gridmarthe/lecsem/__init__.py
gridmarthe/operasem/geometry.py
gridmarthe/operasem/gis.py
gridmarthe/operasem/interp.py
gridmarthe/operasem/__init__.py
gridmarthe/scripts/cleanmgrid.py
gridmarthe/scripts/martshp.py
gridmarthe/scripts/ncmart.py
gridmarthe/scripts/__init__.py
gridmarthe-0.1.3.dist-info/COPYING
gridmarthe-0.1.3.dist-info/DELVEWHEEL
gridmarthe-0.1.3.dist-info/entry_points.txt
gridmarthe-0.1.3.dist-info/METADATA
gridmarthe-0.1.3.dist-info/RECORD
gridmarthe-0.1.3.dist-info/WHEEL
gridmarthe.libs/libgcc_s_seh-1-f2b6825d483bdf14050493af93b5997d.dll
gridmarthe.libs/libgfortran-5-32e30e27ac3d589b7573e438f9e5beb0.dll
gridmarthe.libs/libquadmath-0-ef37afe3a7afa359ebec10dc433d75f5.dll
gridmarthe.libs/libwinpthread-1-e01b8e85fd67c2b861f64d4ccc7df607.dll
