Metadata-Version: 2.1
Name: gridmarthe
Version: 0.1.3
Summary: python package to read/write/manage Marthe Grids
Keywords: hydrology,groundwater,modelling
Author-Email: Adrien Manlay <a.manlay@brgm.fr>, Jean-Pierre Vergnes <jp.vergnes@brgm.fr>
License:                     GNU GENERAL PUBLIC LICENSE
Classifier: License :: OSI Approved :: GNU General Public License v3 or later (GPLv3+)
Classifier: Programming Language :: Python :: 3
Classifier: Programming Language :: Python :: 3 :: Only
Classifier: Programming Language :: Python :: Implementation :: CPython
Classifier: Programming Language :: Fortran
Classifier: Operating System :: Unix
Classifier: Operating System :: POSIX :: Linux
Classifier: Operating System :: MacOS
Classifier: Operating System :: Microsoft :: Windows
Classifier: Topic :: Scientific/Engineering
Classifier: Topic :: Scientific/Engineering :: Hydrology
Classifier: Topic :: Software Development
Classifier: Intended Audience :: Science/Research
Classifier: Intended Audience :: Developers
Classifier: Development Status :: 4 - Beta
Project-URL: Homepage, https://gitlab.com/brgm/hydrogeological-modelling/marthe-tools/gridmarthe
Project-URL: Issues, https://gitlab.com/brgm/hydrogeological-modelling/marthe-tools/gridmarthe/-/issues
Project-URL: Changelog, https://gitlab.com/brgm/hydrogeological-modelling/marthe-tools/gridmarthe/-/blob/main/changelog.rst
Project-URL: Documentation, https://gridmarthe.readthedocs.io/en/latest/
Requires-Python: >=3.10
Requires-Dist: numpy
Requires-Dist: pandas
Requires-Dist: h5netcdf
Requires-Dist: xarray
Requires-Dist: pyproj
Requires-Dist: shapely
Requires-Dist: matplotlib
Requires-Dist: geopandas
Provides-Extra: gis
Requires-Dist: rioxarray; extra == "gis"
Requires-Dist: rasterio; extra == "gis"
Provides-Extra: doc
Requires-Dist: sphinx; extra == "doc"
Requires-Dist: pydata_sphinx_theme; extra == "doc"
Requires-Dist: sphinx-copybutton; extra == "doc"
Requires-Dist: sphinx_design; extra == "doc"
Requires-Dist: sphinxcontrib-bibtex; extra == "doc"
Requires-Dist: myst_nb; extra == "doc"
